CHANGES.txt
LICENSE
MANIFEST.in
README.md
README.rst
setup.cfg
setup.py
django_scraper.egg-info/PKG-INFO
django_scraper.egg-info/SOURCES.txt
django_scraper.egg-info/dependency_links.txt
django_scraper.egg-info/requires.txt
django_scraper.egg-info/top_level.txt
scraper/__init__.py
scraper/admin.py
scraper/base.py
scraper/config.py
scraper/models.py
scraper/signals.py
scraper/tests.py
scraper/urls.py
scraper/utils.py
scraper/management/__init__.py
scraper/management/commands/__init__.py
scraper/management/commands/run_scraper.py
scraper/migrations/0001_initial.py
scraper/migrations/__init__.py
scraper/test_data/medium_shiftmessenger.jpg
scraper/test_data/simple_page.txt
scraper/test_data/yc.0.html
scraper/test_data/yc.1.html
scraper/test_data/yc.2.html
scraper/test_data/yc.a0.html
scraper/test_data/yc.a1.html
scraper/test_data/yc.a2.html