Metadata-Version: 1.0
Name: django-scraper
Version: 0.3.0
Summary: Django application which crawls and downloads online content following instructions
Home-page: https://github.com/zniper/django-scraper
Author: Ha Pham
Author-email: me@zniper.net
License: The MIT License (MIT)
Keywords: crawl scraper spider web pages data extract collect
Platform: UNKNOWN
